<?xml version="1.0" encoding="UTF-8"?>
<!-- Copyright (c) railML.org e.V. Dresden/Germany; All Rights Reserved.
     This work is licensed under the restricted CreativeCommons Attribution-NonCommercial-NoDerivatives 4.0 International License with additional license conditions of railML.org.
     For further information see: https://www.railml.org/licence
     Content of this file: XML Code List for railML(R) Definition of train clearance gauge codes, used by infrastructure sub schema (IS), rollingstock sub schema (RS) and timetable sub schema (TT) -->
<trainClearanceGaugeList xmlns="https://www.railml.org/schemas/lists" xmlns:xsi="http://www.w3.org/2001/XMLSchema-instance" xsi:schemaLocation="https://www.railml.org/schemas/lists TrainClearanceGauges.xsd">
  <trainClearanceGauge code="GA">
    <description>structure gauge GA according to European standard</description>
    <validFor>interoperable</validFor>
  </trainClearanceGauge>
  <trainClearanceGauge code="GB">
    <description>structure gauge GB according to European standard</description>
    <validFor>interoperable</validFor>
  </trainClearanceGauge>
  <trainClearanceGauge code="GC">
    <description>structure gauge GC according to European standard</description>
    <validFor>interoperable</validFor>
  </trainClearanceGauge>
  <trainClearanceGauge code="G1">
    <description>Multilateral gauge or international gauge G1 other than GA, GB and GC as defined in European standard.</description>
    <validFor>interoperable</validFor>
  </trainClearanceGauge>
  <trainClearanceGauge code="G2">
    <description>Multilateral gauge or international gauge G2 other than GA, GB and GC as defined in European standard.</description>
    <validFor>multinational</validFor>
  </trainClearanceGauge>
  <trainClearanceGauge code="GB1">
    <description>Multilateral gauge or international gauge GB1 other than GA, GB and GC as defined in European standard.</description>
    <validFor>multinational</validFor>
  </trainClearanceGauge>
  <trainClearanceGauge code="GB2">
    <description>Multilateral gauge or international gauge GB2 other than GA, GB and GC as defined in European standard.</description>
    <validFor>multinational</validFor>
  </trainClearanceGauge>
  <trainClearanceGauge code="BE1">
    <description>Domestic gauge BE1 as defined in European standard or national regulation.</description>
    <validFor>national</validFor>
  </trainClearanceGauge>
  <trainClearanceGauge code="BE2">
    <description>Domestic gauge BE2 as defined in European standard or national regulation</description>
    <validFor>national</validFor>
  </trainClearanceGauge>
  <trainClearanceGauge code="BE3">
    <description>Domestic gauge BE3 as defined in European standard or national regulation</description>
    <validFor>national</validFor>
  </trainClearanceGauge>
  <trainClearanceGauge code="FR-3.3">
    <description>Domestic gauge FR-3.3 as defined in European standard or national regulation</description>
    <validFor>national</validFor>
  </trainClearanceGauge>
  <trainClearanceGauge code="PTb">
    <description>Domestic gauge PTb as defined in European standard or national regulation</description>
    <validFor>national</validFor>
  </trainClearanceGauge>
  <trainClearanceGauge code="PTb+">
    <description>Domestic gauge PTb+ as defined in European standard or national regulation</description>
    <validFor>national</validFor>
  </trainClearanceGauge>
  <trainClearanceGauge code="PTc">
    <description>Domestic gauge PTc as defined in European standard or national regulation</description>
    <validFor>national</validFor>
  </trainClearanceGauge>
  <trainClearanceGauge code="FIN1">
    <description>Domestic gauge FIN1 as defined in European standard or national regulation</description>
    <validFor>national</validFor>
  </trainClearanceGauge>
  <trainClearanceGauge code="SEa">
    <description>Domestic gauge SEa as defined in European standard or national regulation</description>
    <validFor>national</validFor>
  </trainClearanceGauge>
  <trainClearanceGauge code="SEc">
    <description>Domestic gauge SEc as defined in European standard or national regulation</description>
    <validFor>national</validFor>
  </trainClearanceGauge>
  <trainClearanceGauge code="DE1">
    <description>Domestic gauge DE1 as defined in European standard or national regulation</description>
    <validFor>national</validFor>
  </trainClearanceGauge>
  <trainClearanceGauge code="DE2">
    <description>Domestic gauge DE2 as defined in European standard or national regulation</description>
    <validFor>national</validFor>
  </trainClearanceGauge>
  <trainClearanceGauge code="DE3">
    <description>Domestic gauge DE3 as defined in European standard or national regulation</description>
    <validFor>interoperable</validFor>
  </trainClearanceGauge>
  <trainClearanceGauge code="Z-GCD">
    <description>Domestic gauge Z-GCD as defined in European standard or national regulation</description>
    <validFor>national</validFor>
  </trainClearanceGauge>
  <trainClearanceGauge code="UK1">
    <description>Domestic gauge UK1 as defined in European standard or national regulation</description>
    <validFor>national</validFor>
  </trainClearanceGauge>
  <trainClearanceGauge code="UK1[D]">
    <description>Domestic gauge UK1[D] as defined in European standard or national regulation</description>
    <validFor>national</validFor>
  </trainClearanceGauge>
  <trainClearanceGauge code="W6">
    <description>Domestic gauge W6 as defined in European standard or national regulation</description>
    <validFor>national</validFor>
  </trainClearanceGauge>
  <trainClearanceGauge code="FS">
    <description>Domestic gauge FS (Italy) as defined in European standard or national regulation</description>
    <validFor>national</validFor>
  </trainClearanceGauge>
  <trainClearanceGauge code="S">
    <description>Domestic gauge S (1520 broad gauge) as defined in European standard or national regulation</description>
    <validFor>interoperable</validFor>
  </trainClearanceGauge>
  <trainClearanceGauge code="GHE16">
    <description>Domestic gauge GHE16 (Spain) as defined in European standard or national regulation</description>
    <validFor>national</validFor>
  </trainClearanceGauge>
  <trainClearanceGauge code="GEB16">
    <description>Domestic gauge GEB16 (Spain) as defined in European standard or national regulation</description>
    <validFor>national</validFor>
  </trainClearanceGauge>
  <trainClearanceGauge code="GEC16">
    <description>Domestic gauge GEC16 (Spain) as defined in European standard or national regulation</description>
    <validFor>national</validFor>
  </trainClearanceGauge>
  <trainClearanceGauge code="IRL1">
    <description>Domestic gauge IRL1 (Ireland) as defined in European standard or national regulation</description>
    <validFor>interoperable</validFor>
  </trainClearanceGauge>
  <trainClearanceGauge code="IRL2">
    <description>Domestic gauge IRL2 (Ireland) as defined in European standard or national regulation</description>
    <validFor>national</validFor>
  </trainClearanceGauge>
  <trainClearanceGauge code="IRL3">
    <description>Domestic gauge IRL3 (Ireland) as defined in European standard or national regulation</description>
    <validFor>national</validFor>
  </trainClearanceGauge>
</trainClearanceGaugeList>
